aarghparse/__init__.py
aarghparse/arguments.py
aarghparse/cli.py
aarghparse/func_utils.py
aarghparse/parsers.py
aarghparse-0.2.0.dist-info/METADATA
aarghparse-0.2.0.dist-info/WHEEL
aarghparse-0.2.0.dist-info/top_level.txt
aarghparse-0.2.0.dist-info/RECORD
