Metadata-Version: 2.1
Name: aarghparse
Version: 0.2.0
Summary: A collection of argparse extensions
Home-page: https://github.com/jbasko/aarghparse
Author: Jazeps Basko
Author-email: jazeps.basko@gmail.com
Maintainer: Jazeps Basko
Maintainer-email: jazeps.basko@gmail.com
License: MIT
Keywords: argparse cli
Platform: UNKNOWN
Classifier: Development Status :: 3 - Alpha
Classifier: Intended Audience :: Developers
Classifier: Topic :: Software Development :: Libraries
Classifier: Programming Language :: Python
Classifier: Programming Language :: Python :: 3
Classifier: Programming Language :: Python :: 3.6
Classifier: Programming Language :: Python :: 3.7
Classifier: License :: OSI Approved :: MIT License
Requires-Python: >=3.6.0
